{"type": "directory", "dataset_id": "PN000014 multimodal total-body 18F-FDG PET-CT-MRI - static images", "dataset_version": "V1", "children": [{"type": "file", "dataset_id": "PN000014 multimodal total-body 18F-FDG PET-CT-MRI - static images", "dataset_version": "V1", "path": "sub-088/ses-vida/anat/sub-088_ses-vida_task-rest_acq-FASTVIEW_T1w.nii.gz", "contentbytesize": 1780331.0, "isPartOf": "PN000014 multimodal total-body 18F-FDG PET-CT-MRI - static images", "metadata_sources": {"sources": [{"source_name": "Rigshospitalet", "source_version": "V1", "agent_name": "Christian Hinge"}]}, "name": "sub-088_ses-vida_task-rest_acq-FASTVIEW_T1w.nii.gz"}, {"type": "file", "dataset_id": "PN000014 multimodal total-body 18F-FDG PET-CT-MRI - static images", "dataset_version": "V1", "path": "sub-088/ses-vida/anat/sub-088_ses-vida_task-breathhold_acq-DIXONbodyIN_chunk-3_T1w.nii.gz", "contentbytesize": 6524516.0, "isPartOf": "PN000014 multimodal total-body 18F-FDG PET-CT-MRI - static images", "metadata_sources": {"sources": [{"source_name": "Rigshospitalet", "source_version": "V1", "agent_name": "Christian Hinge"}]}, "name": "sub-088_ses-vida_task-breathhold_acq-DIXONbodyIN_chunk-3_T1w.nii.gz"}, {"type": "file", "dataset_id": "PN000014 multimodal total-body 18F-FDG PET-CT-MRI - static images", "dataset_version": "V1", "path": "sub-088/ses-vida/anat/sub-088_ses-vida_task-breathhold_acq-DIXONbodyOUT_chunk-2_T1w.nii.gz", "contentbytesize": 7895878.0, "isPartOf": "PN000014 multimodal total-body 18F-FDG PET-CT-MRI - static images", "metadata_sources": {"sources": [{"source_name": "Rigshospitalet", "source_version": "V1", "agent_name": "Christian Hinge"}]}, "name": "sub-088_ses-vida_task-breathhold_acq-DIXONbodyOUT_chunk-2_T1w.nii.gz"}, {"type": "file", "dataset_id": "PN000014 multimodal total-body 18F-FDG PET-CT-MRI - static images", "dataset_version": "V1", "path": "sub-088/ses-vida/anat/sub-088_ses-vida_task-breathhold_acq-DIXONbodyIN_chunk-3_T1w.json", "contentbytesize": 2721.0, "isPartOf": "PN000014 multimodal total-body 18F-FDG PET-CT-MRI - static images", "metadata_sources": {"sources": [{"source_name": "Rigshospitalet", "source_version": "V1", "agent_name": "Christian Hinge"}]}, "name": "sub-088_ses-vida_task-breathhold_acq-DIXONbodyIN_chunk-3_T1w.json"}, {"type": "file", "dataset_id": "PN000014 multimodal total-body 18F-FDG PET-CT-MRI - static images", "dataset_version": "V1", "path": "sub-088/ses-vida/anat/sub-088_ses-vida_task-breathhold_acq-DIXONbodyIN_chunk-2_T1w.nii.gz", "contentbytesize": 7634967.0, "isPartOf": "PN000014 multimodal total-body 18F-FDG PET-CT-MRI - static images", "metadata_sources": {"sources": [{"source_name": "Rigshospitalet", "source_version": "V1", "agent_name": "Christian Hinge"}]}, "name": "sub-088_ses-vida_task-breathhold_acq-DIXONbodyIN_chunk-2_T1w.nii.gz"}, {"type": "file", "dataset_id": "PN000014 multimodal total-body 18F-FDG PET-CT-MRI - static images", "dataset_version": "V1", "path": "sub-088/ses-vida/anat/sub-088_ses-vida_task-breathhold_acq-DIXONbodyIN_T1w.nii.gz", "contentbytesize": 23708624.0, "isPartOf": "PN000014 multimodal total-body 18F-FDG PET-CT-MRI - static images", "metadata_sources": {"sources": [{"source_name": "Rigshospitalet", "source_version": "V1", "agent_name": "Christian Hinge"}]}, "name": "sub-088_ses-vida_task-breathhold_acq-DIXONbodyIN_T1w.nii.gz"}, {"type": "file", "dataset_id": "PN000014 multimodal total-body 18F-FDG PET-CT-MRI - static images", "dataset_version": "V1", "path": "sub-088/ses-vida/anat/sub-088_ses-vida_task-rest_acq-FASTVIEW_T1w.json", "contentbytesize": 2238.0, "isPartOf": "PN000014 multimodal total-body 18F-FDG PET-CT-MRI - static images", "metadata_sources": {"sources": [{"source_name": "Rigshospitalet", "source_version": "V1", "agent_name": "Christian Hinge"}]}, "name": "sub-088_ses-vida_task-rest_acq-FASTVIEW_T1w.json"}, {"type": "file", "dataset_id": "PN000014 multimodal total-body 18F-FDG PET-CT-MRI - static images", "dataset_version": "V1", "path": "sub-088/ses-vida/anat/sub-088_ses-vida_task-breathhold_acq-DIXONheadOUT_T1w.nii.gz", "contentbytesize": 4445594.0, "isPartOf": "PN000014 multimodal total-body 18F-FDG PET-CT-MRI - static images", "metadata_sources": {"sources": [{"source_name": "Rigshospitalet", "source_version": "V1", "agent_name": "Christian Hinge"}]}, "name": "sub-088_ses-vida_task-breathhold_acq-DIXONheadOUT_T1w.nii.gz"}, {"type": "file", "dataset_id": "PN000014 multimodal total-body 18F-FDG PET-CT-MRI - static images", "dataset_version": "V1", "path": "sub-088/ses-vida/anat/sub-088_ses-vida_task-rest_acq-MPRAGE_T1w.json", "contentbytesize": 2590.0, "isPartOf": "PN000014 multimodal total-body 18F-FDG PET-CT-MRI - static images", "metadata_sources": {"sources": [{"source_name": "Rigshospitalet", "source_version": "V1", "agent_name": "Christian Hinge"}]}, "name": "sub-088_ses-vida_task-rest_acq-MPRAGE_T1w.json"}, {"type": "file", "dataset_id": "PN000014 multimodal total-body 18F-FDG PET-CT-MRI - static images", "dataset_version": "V1", "path": "sub-088/ses-vida/anat/sub-088_ses-vida_task-breathhold_acq-DIXONbodyOUT_chunk-1_T1w.nii.gz", "contentbytesize": 8909037.0, "isPartOf": "PN000014 multimodal total-body 18F-FDG PET-CT-MRI - static images", "metadata_sources": {"sources": [{"source_name": "Rigshospitalet", "source_version": "V1", "agent_name": "Christian Hinge"}]}, "name": "sub-088_ses-vida_task-breathhold_acq-DIXONbodyOUT_chunk-1_T1w.nii.gz"}, {"type": "file", "dataset_id": "PN000014 multimodal total-body 18F-FDG PET-CT-MRI - static images", "dataset_version": "V1", "path": "sub-088/ses-vida/anat/sub-088_ses-vida_task-breathhold_acq-DIXONbodyIN_chunk-0_T1w.json", "contentbytesize": 2862.0, "isPartOf": "PN000014 multimodal total-body 18F-FDG PET-CT-MRI - static images", "metadata_sources": {"sources": [{"source_name": "Rigshospitalet", "source_version": "V1", "agent_name": "Christian Hinge"}]}, "name": "sub-088_ses-vida_task-breathhold_acq-DIXONbodyIN_chunk-0_T1w.json"}, {"type": "file", "dataset_id": "PN000014 multimodal total-body 18F-FDG PET-CT-MRI - static images", "dataset_version": "V1", "path": "sub-088/ses-vida/anat/sub-088_ses-vida_task-breathhold_acq-DIXONbodyOUT_T1w.json", "contentbytesize": 2724.0, "isPartOf": "PN000014 multimodal total-body 18F-FDG PET-CT-MRI - static images", "metadata_sources": {"sources": [{"source_name": "Rigshospitalet", "source_version": "V1", "agent_name": "Christian Hinge"}]}, "name": "sub-088_ses-vida_task-breathhold_acq-DIXONbodyOUT_T1w.json"}, {"type": "file", "dataset_id": "PN000014 multimodal total-body 18F-FDG PET-CT-MRI - static images", "dataset_version": "V1", "path": "sub-088/ses-vida/anat/sub-088_ses-vida_task-breathhold_acq-DIXONbodyIN_chunk-2_T1w.json", "contentbytesize": 2722.0, "isPartOf": "PN000014 multimodal total-body 18F-FDG PET-CT-MRI - static images", "metadata_sources": {"sources": [{"source_name": "Rigshospitalet", "source_version": "V1", "agent_name": "Christian Hinge"}]}, "name": "sub-088_ses-vida_task-breathhold_acq-DIXONbodyIN_chunk-2_T1w.json"}, {"type": "file", "dataset_id": "PN000014 multimodal total-body 18F-FDG PET-CT-MRI - static images", "dataset_version": "V1", "path": "sub-088/ses-vida/anat/sub-088_ses-vida_task-breathhold_acq-DIXONbodyOUT_chunk-0_T1w.nii.gz", "contentbytesize": 4363301.0, "isPartOf": "PN000014 multimodal total-body 18F-FDG PET-CT-MRI - static images", "metadata_sources": {"sources": [{"source_name": "Rigshospitalet", "source_version": "V1", "agent_name": "Christian Hinge"}]}, "name": "sub-088_ses-vida_task-breathhold_acq-DIXONbodyOUT_chunk-0_T1w.nii.gz"}, {"type": "file", "dataset_id": "PN000014 multimodal total-body 18F-FDG PET-CT-MRI - static images", "dataset_version": "V1", "path": "sub-088/ses-vida/anat/sub-088_ses-vida_task-breathhold_acq-DIXONbodyOUT_T1w.nii.gz", "contentbytesize": 24350953.0, "isPartOf": "PN000014 multimodal total-body 18F-FDG PET-CT-MRI - static images", "metadata_sources": {"sources": [{"source_name": "Rigshospitalet", "source_version": "V1", "agent_name": "Christian Hinge"}]}, "name": "sub-088_ses-vida_task-breathhold_acq-DIXONbodyOUT_T1w.nii.gz"}, {"type": "file", "dataset_id": "PN000014 multimodal total-body 18F-FDG PET-CT-MRI - static images", "dataset_version": "V1", "path": "sub-088/ses-vida/anat/sub-088_ses-vida_task-breathhold_acq-DIXONheadIN_T1w.json", "contentbytesize": 2781.0, "isPartOf": "PN000014 multimodal total-body 18F-FDG PET-CT-MRI - static images", "metadata_sources": {"sources": [{"source_name": "Rigshospitalet", "source_version": "V1", "agent_name": "Christian Hinge"}]}, "name": "sub-088_ses-vida_task-breathhold_acq-DIXONheadIN_T1w.json"}, {"type": "file", "dataset_id": "PN000014 multimodal total-body 18F-FDG PET-CT-MRI - static images", "dataset_version": "V1", "path": "sub-088/ses-vida/anat/sub-088_ses-vida_task-breathhold_acq-DIXONbodyOUT_chunk-2_T1w.json", "contentbytesize": 2753.0, "isPartOf": "PN000014 multimodal total-body 18F-FDG PET-CT-MRI - static images", "metadata_sources": {"sources": [{"source_name": "Rigshospitalet", "source_version": "V1", "agent_name": "Christian Hinge"}]}, "name": "sub-088_ses-vida_task-breathhold_acq-DIXONbodyOUT_chunk-2_T1w.json"}, {"type": "file", "dataset_id": "PN000014 multimodal total-body 18F-FDG PET-CT-MRI - static images", "dataset_version": "V1", "path": "sub-088/ses-vida/anat/sub-088_ses-vida_task-breathhold_acq-DIXONbodyIN_chunk-1_T1w.json", "contentbytesize": 2722.0, "isPartOf": "PN000014 multimodal total-body 18F-FDG PET-CT-MRI - static images", "metadata_sources": {"sources": [{"source_name": "Rigshospitalet", "source_version": "V1", "agent_name": "Christian Hinge"}]}, "name": "sub-088_ses-vida_task-breathhold_acq-DIXONbodyIN_chunk-1_T1w.json"}, {"type": "file", "dataset_id": "PN000014 multimodal total-body 18F-FDG PET-CT-MRI - static images", "dataset_version": "V1", "path": "sub-088/ses-vida/anat/sub-088_ses-vida_task-breathhold_acq-DIXONbodyOUT_chunk-1_T1w.json", "contentbytesize": 2752.0, "isPartOf": "PN000014 multimodal total-body 18F-FDG PET-CT-MRI - static images", "metadata_sources": {"sources": [{"source_name": "Rigshospitalet", "source_version": "V1", "agent_name": "Christian Hinge"}]}, "name": "sub-088_ses-vida_task-breathhold_acq-DIXONbodyOUT_chunk-1_T1w.json"}, {"type": "file", "dataset_id": "PN000014 multimodal total-body 18F-FDG PET-CT-MRI - static images", "dataset_version": "V1", "path": "sub-088/ses-vida/anat/sub-088_ses-vida_task-breathhold_acq-DIXONbodyIN_chunk-0_T1w.nii.gz", "contentbytesize": 4301692.0, "isPartOf": "PN000014 multimodal total-body 18F-FDG PET-CT-MRI - static images", "metadata_sources": {"sources": [{"source_name": "Rigshospitalet", "source_version": "V1", "agent_name": "Christian Hinge"}]}, "name": "sub-088_ses-vida_task-breathhold_acq-DIXONbodyIN_chunk-0_T1w.nii.gz"}, {"type": "file", "dataset_id": "PN000014 multimodal total-body 18F-FDG PET-CT-MRI - static images", "dataset_version": "V1", "path": "sub-088/ses-vida/anat/sub-088_ses-vida_task-breathhold_acq-DIXONbodyOUT_chunk-3_T1w.json", "contentbytesize": 2752.0, "isPartOf": "PN000014 multimodal total-body 18F-FDG PET-CT-MRI - static images", "metadata_sources": {"sources": [{"source_name": "Rigshospitalet", "source_version": "V1", "agent_name": "Christian Hinge"}]}, "name": "sub-088_ses-vida_task-breathhold_acq-DIXONbodyOUT_chunk-3_T1w.json"}, {"type": "file", "dataset_id": "PN000014 multimodal total-body 18F-FDG PET-CT-MRI - static images", "dataset_version": "V1", "path": "sub-088/ses-vida/anat/sub-088_ses-vida_task-breathhold_acq-DIXONbodyOUT_chunk-0_T1w.json", "contentbytesize": 2893.0, "isPartOf": "PN000014 multimodal total-body 18F-FDG PET-CT-MRI - static images", "metadata_sources": {"sources": [{"source_name": "Rigshospitalet", "source_version": "V1", "agent_name": "Christian Hinge"}]}, "name": "sub-088_ses-vida_task-breathhold_acq-DIXONbodyOUT_chunk-0_T1w.json"}, {"type": "file", "dataset_id": "PN000014 multimodal total-body 18F-FDG PET-CT-MRI - static images", "dataset_version": "V1", "path": "sub-088/ses-vida/anat/sub-088_ses-vida_task-breathhold_acq-DIXONheadIN_T1w.nii.gz", "contentbytesize": 4464446.0, "isPartOf": "PN000014 multimodal total-body 18F-FDG PET-CT-MRI - static images", "metadata_sources": {"sources": [{"source_name": "Rigshospitalet", "source_version": "V1", "agent_name": "Christian Hinge"}]}, "name": "sub-088_ses-vida_task-breathhold_acq-DIXONheadIN_T1w.nii.gz"}, {"type": "file", "dataset_id": "PN000014 multimodal total-body 18F-FDG PET-CT-MRI - static images", "dataset_version": "V1", "path": "sub-088/ses-vida/anat/sub-088_ses-vida_task-breathhold_acq-DIXONbodyIN_chunk-1_T1w.nii.gz", "contentbytesize": 8786028.0, "isPartOf": "PN000014 multimodal total-body 18F-FDG PET-CT-MRI - static images", "metadata_sources": {"sources": [{"source_name": "Rigshospitalet", "source_version": "V1", "agent_name": "Christian Hinge"}]}, "name": "sub-088_ses-vida_task-breathhold_acq-DIXONbodyIN_chunk-1_T1w.nii.gz"}, {"type": "file", "dataset_id": "PN000014 multimodal total-body 18F-FDG PET-CT-MRI - static images", "dataset_version": "V1", "path": "sub-088/ses-vida/anat/sub-088_ses-vida_task-breathhold_acq-DIXONbodyOUT_chunk-3_T1w.nii.gz", "contentbytesize": 6824982.0, "isPartOf": "PN000014 multimodal total-body 18F-FDG PET-CT-MRI - static images", "metadata_sources": {"sources": [{"source_name": "Rigshospitalet", "source_version": "V1", "agent_name": "Christian Hinge"}]}, "name": "sub-088_ses-vida_task-breathhold_acq-DIXONbodyOUT_chunk-3_T1w.nii.gz"}, {"type": "file", "dataset_id": "PN000014 multimodal total-body 18F-FDG PET-CT-MRI - static images", "dataset_version": "V1", "path": "sub-088/ses-vida/anat/sub-088_ses-vida_task-breathhold_acq-DIXONbodyIN_T1w.json", "contentbytesize": 2722.0, "isPartOf": "PN000014 multimodal total-body 18F-FDG PET-CT-MRI - static images", "metadata_sources": {"sources": [{"source_name": "Rigshospitalet", "source_version": "V1", "agent_name": "Christian Hinge"}]}, "name": "sub-088_ses-vida_task-breathhold_acq-DIXONbodyIN_T1w.json"}, {"type": "file", "dataset_id": "PN000014 multimodal total-body 18F-FDG PET-CT-MRI - static images", "dataset_version": "V1", "path": "sub-088/ses-vida/anat/sub-088_ses-vida_task-rest_acq-MPRAGE_T1w.nii.gz", "contentbytesize": 44736911.0, "isPartOf": "PN000014 multimodal total-body 18F-FDG PET-CT-MRI - static images", "metadata_sources": {"sources": [{"source_name": "Rigshospitalet", "source_version": "V1", "agent_name": "Christian Hinge"}]}, "name": "sub-088_ses-vida_task-rest_acq-MPRAGE_T1w.nii.gz"}, {"type": "file", "dataset_id": "PN000014 multimodal total-body 18F-FDG PET-CT-MRI - static images", "dataset_version": "V1", "path": "sub-088/ses-vida/anat/sub-088_ses-vida_task-breathhold_acq-DIXONheadOUT_T1w.json", "contentbytesize": 2812.0, "isPartOf": "PN000014 multimodal total-body 18F-FDG PET-CT-MRI - static images", "metadata_sources": {"sources": [{"source_name": "Rigshospitalet", "source_version": "V1", "agent_name": "Christian Hinge"}]}, "name": "sub-088_ses-vida_task-breathhold_acq-DIXONheadOUT_T1w.json"}], "path": "sub-088/ses-vida/anat", "name": "anat"}