{"type": "directory", "dataset_id": "PN000023 Familial risk for affective disorders and serotonergic brain architecture", "dataset_version": "V1", "children": [{"type": "directory", "name": "anat", "path": "sub-10795/anat", "dataset_id": "PN000023 Familial risk for affective disorders and serotonergic brain architecture", "dataset_version": "V1"}, {"type": "directory", "name": "fmap", "path": "sub-10795/fmap", "dataset_id": "PN000023 Familial risk for affective disorders and serotonergic brain architecture", "dataset_version": "V1"}, {"type": "directory", "name": "pet", "path": "sub-10795/pet", "dataset_id": "PN000023 Familial risk for affective disorders and serotonergic brain architecture", "dataset_version": "V1"}], "path": "sub-10795", "name": "sub-10795"}