{"type": "directory", "dataset_id": "PN000018 Gonadotrophin releasing hormone agonist (GnRHa) sex-hormone manipulation model of risk for depression", "dataset_version": "V1", "children": [{"type": "file", "dataset_id": "PN000018 Gonadotrophin releasing hormone agonist (GnRHa) sex-hormone manipulation model of risk for depression", "dataset_version": "V1", "path": "sub-50806/ses-rescan/fmap/sub-50806_ses-rescan_phasediff.json", "contentbytesize": 2492.0, "isPartOf": "PN000018 Gonadotrophin releasing hormone agonist (GnRHa) sex-hormone manipulation model of risk for depression", "metadata_sources": {"sources": [{"source_name": "Local_Processing", "source_version": "V1", "agent_name": "Pipeline"}]}, "name": "sub-50806_ses-rescan_phasediff.json"}, {"type": "file", "dataset_id": "PN000018 Gonadotrophin releasing hormone agonist (GnRHa) sex-hormone manipulation model of risk for depression", "dataset_version": "V1", "path": "sub-50806/ses-rescan/fmap/sub-50806_ses-rescan_magnitude1.json", "contentbytesize": 2400.0, "isPartOf": "PN000018 Gonadotrophin releasing hormone agonist (GnRHa) sex-hormone manipulation model of risk for depression", "metadata_sources": {"sources": [{"source_name": "Local_Processing", "source_version": "V1", "agent_name": "Pipeline"}]}, "name": "sub-50806_ses-rescan_magnitude1.json"}, {"type": "file", "dataset_id": "PN000018 Gonadotrophin releasing hormone agonist (GnRHa) sex-hormone manipulation model of risk for depression", "dataset_version": "V1", "path": "sub-50806/ses-rescan/fmap/sub-50806_ses-rescan_magnitude2.json", "contentbytesize": 2430.0, "isPartOf": "PN000018 Gonadotrophin releasing hormone agonist (GnRHa) sex-hormone manipulation model of risk for depression", "metadata_sources": {"sources": [{"source_name": "Local_Processing", "source_version": "V1", "agent_name": "Pipeline"}]}, "name": "sub-50806_ses-rescan_magnitude2.json"}, {"type": "file", "dataset_id": "PN000018 Gonadotrophin releasing hormone agonist (GnRHa) sex-hormone manipulation model of risk for depression", "dataset_version": "V1", "path": "sub-50806/ses-rescan/fmap/sub-50806_ses-rescan_magnitude2.nii.gz", "contentbytesize": 242491.0, "isPartOf": "PN000018 Gonadotrophin releasing hormone agonist (GnRHa) sex-hormone manipulation model of risk for depression", "metadata_sources": {"sources": [{"source_name": "Local_Processing", "source_version": "V1", "agent_name": "Pipeline"}]}, "name": "sub-50806_ses-rescan_magnitude2.nii.gz"}, {"type": "file", "dataset_id": "PN000018 Gonadotrophin releasing hormone agonist (GnRHa) sex-hormone manipulation model of risk for depression", "dataset_version": "V1", "path": "sub-50806/ses-rescan/fmap/sub-50806_ses-rescan_magnitude1.nii.gz", "contentbytesize": 245286.0, "isPartOf": "PN000018 Gonadotrophin releasing hormone agonist (GnRHa) sex-hormone manipulation model of risk for depression", "metadata_sources": {"sources": [{"source_name": "Local_Processing", "source_version": "V1", "agent_name": "Pipeline"}]}, "name": "sub-50806_ses-rescan_magnitude1.nii.gz"}, {"type": "file", "dataset_id": "PN000018 Gonadotrophin releasing hormone agonist (GnRHa) sex-hormone manipulation model of risk for depression", "dataset_version": "V1", "path": "sub-50806/ses-rescan/fmap/sub-50806_ses-rescan_phasediff.nii.gz", "contentbytesize": 299044.0, "isPartOf": "PN000018 Gonadotrophin releasing hormone agonist (GnRHa) sex-hormone manipulation model of risk for depression", "metadata_sources": {"sources": [{"source_name": "Local_Processing", "source_version": "V1", "agent_name": "Pipeline"}]}, "name": "sub-50806_ses-rescan_phasediff.nii.gz"}], "path": "sub-50806/ses-rescan/fmap", "name": "fmap"}