{"type": "directory", "dataset_id": "PN000001: OpenNeuroPET Phantoms", "dataset_version": "V1", "children": [{"type": "file", "dataset_id": "PN000001: OpenNeuroPET Phantoms", "dataset_version": "V1", "path": "sub-SiemensBiographNIMH/pet/sub-SiemensBiographNIMH_pet.json", "contentbytesize": 1518, "metadata_sources": {"sources": [{"source_name": "OpenNeuro_PET", "source_version": "V1", "agent_name": "Cyril Pernet"}]}, "name": "sub-SiemensBiographNIMH_pet.json"}, {"type": "file", "dataset_id": "PN000001: OpenNeuroPET Phantoms", "dataset_version": "V1", "path": "sub-SiemensBiographNIMH/pet/sub-SiemensBiographNIMH_pet.nii.gz", "contentbytesize": 11284091, "metadata_sources": {"sources": [{"source_name": "OpenNeuro_PET", "source_version": "V1", "agent_name": "Cyril Pernet"}]}, "name": "sub-SiemensBiographNIMH_pet.nii.gz"}], "path": "sub-SiemensBiographNIMH/pet", "name": "pet"}