{"type": "directory", "dataset_id": "PN000024 A clinical brain MRI dataset of polymicrogyria in patients suspected of epilepsy", "dataset_version": "V1", "children": [{"type": "file", "dataset_id": "PN000024 A clinical brain MRI dataset of polymicrogyria in patients suspected of epilepsy", "dataset_version": "V1", "path": "sub-EP033801/ses-001/anat/sub-EP033801_ses-001_FLAIR.json", "contentbytesize": 2143.0, "isPartOf": "PN000024 A clinical brain MRI dataset of polymicrogyria in patients suspected of epilepsy", "metadata_sources": {"sources": [{"source_name": "Local_Processing", "source_version": "V1", "agent_name": "Pipeline"}]}, "name": "sub-EP033801_ses-001_FLAIR.json"}, {"type": "file", "dataset_id": "PN000024 A clinical brain MRI dataset of polymicrogyria in patients suspected of epilepsy", "dataset_version": "V1", "path": "sub-EP033801/ses-001/anat/sub-EP033801_ses-001_FLAIR.nii.gz", "contentbytesize": 11810668.0, "isPartOf": "PN000024 A clinical brain MRI dataset of polymicrogyria in patients suspected of epilepsy", "metadata_sources": {"sources": [{"source_name": "Local_Processing", "source_version": "V1", "agent_name": "Pipeline"}]}, "name": "sub-EP033801_ses-001_FLAIR.nii.gz"}, {"type": "file", "dataset_id": "PN000024 A clinical brain MRI dataset of polymicrogyria in patients suspected of epilepsy", "dataset_version": "V1", "path": "sub-EP033801/ses-001/anat/sub-EP033801_ses-001_T1w.json", "contentbytesize": 2039.0, "isPartOf": "PN000024 A clinical brain MRI dataset of polymicrogyria in patients suspected of epilepsy", "metadata_sources": {"sources": [{"source_name": "Local_Processing", "source_version": "V1", "agent_name": "Pipeline"}]}, "name": "sub-EP033801_ses-001_T1w.json"}, {"type": "file", "dataset_id": "PN000024 A clinical brain MRI dataset of polymicrogyria in patients suspected of epilepsy", "dataset_version": "V1", "path": "sub-EP033801/ses-001/anat/sub-EP033801_ses-001_T1w.nii.gz", "contentbytesize": 36169313.0, "isPartOf": "PN000024 A clinical brain MRI dataset of polymicrogyria in patients suspected of epilepsy", "metadata_sources": {"sources": [{"source_name": "Local_Processing", "source_version": "V1", "agent_name": "Pipeline"}]}, "name": "sub-EP033801_ses-001_T1w.nii.gz"}, {"type": "file", "dataset_id": "PN000024 A clinical brain MRI dataset of polymicrogyria in patients suspected of epilepsy", "dataset_version": "V1", "path": "sub-EP033801/ses-001/anat/sub-EP033801_ses-001_T2starw.json", "contentbytesize": 2115.0, "isPartOf": "PN000024 A clinical brain MRI dataset of polymicrogyria in patients suspected of epilepsy", "metadata_sources": {"sources": [{"source_name": "Local_Processing", "source_version": "V1", "agent_name": "Pipeline"}]}, "name": "sub-EP033801_ses-001_T2starw.json"}, {"type": "file", "dataset_id": "PN000024 A clinical brain MRI dataset of polymicrogyria in patients suspected of epilepsy", "dataset_version": "V1", "path": "sub-EP033801/ses-001/anat/sub-EP033801_ses-001_T2starw.nii.gz", "contentbytesize": 44550294.0, "isPartOf": "PN000024 A clinical brain MRI dataset of polymicrogyria in patients suspected of epilepsy", "metadata_sources": {"sources": [{"source_name": "Local_Processing", "source_version": "V1", "agent_name": "Pipeline"}]}, "name": "sub-EP033801_ses-001_T2starw.nii.gz"}, {"type": "file", "dataset_id": "PN000024 A clinical brain MRI dataset of polymicrogyria in patients suspected of epilepsy", "dataset_version": "V1", "path": "sub-EP033801/ses-001/anat/sub-EP033801_ses-001_T2w.json", "contentbytesize": 1956.0, "isPartOf": "PN000024 A clinical brain MRI dataset of polymicrogyria in patients suspected of epilepsy", "metadata_sources": {"sources": [{"source_name": "Local_Processing", "source_version": "V1", "agent_name": "Pipeline"}]}, "name": "sub-EP033801_ses-001_T2w.json"}, {"type": "file", "dataset_id": "PN000024 A clinical brain MRI dataset of polymicrogyria in patients suspected of epilepsy", "dataset_version": "V1", "path": "sub-EP033801/ses-001/anat/sub-EP033801_ses-001_T2w.nii.gz", "contentbytesize": 6794432.0, "isPartOf": "PN000024 A clinical brain MRI dataset of polymicrogyria in patients suspected of epilepsy", "metadata_sources": {"sources": [{"source_name": "Local_Processing", "source_version": "V1", "agent_name": "Pipeline"}]}, "name": "sub-EP033801_ses-001_T2w.nii.gz"}, {"type": "file", "dataset_id": "PN000024 A clinical brain MRI dataset of polymicrogyria in patients suspected of epilepsy", "dataset_version": "V1", "path": "sub-EP033801/ses-001/anat/sub-EP033801_ses-001_run-2_T2w.json", "contentbytesize": 1947.0, "isPartOf": "PN000024 A clinical brain MRI dataset of polymicrogyria in patients suspected of epilepsy", "metadata_sources": {"sources": [{"source_name": "Local_Processing", "source_version": "V1", "agent_name": "Pipeline"}]}, "name": "sub-EP033801_ses-001_run-2_T2w.json"}, {"type": "file", "dataset_id": "PN000024 A clinical brain MRI dataset of polymicrogyria in patients suspected of epilepsy", "dataset_version": "V1", "path": "sub-EP033801/ses-001/anat/sub-EP033801_ses-001_run-2_T2w.nii.gz", "contentbytesize": 14462725.0, "isPartOf": "PN000024 A clinical brain MRI dataset of polymicrogyria in patients suspected of epilepsy", "metadata_sources": {"sources": [{"source_name": "Local_Processing", "source_version": "V1", "agent_name": "Pipeline"}]}, "name": "sub-EP033801_ses-001_run-2_T2w.nii.gz"}], "path": "sub-EP033801/ses-001/anat", "name": "anat"}