{"type": "directory", "dataset_id": "PN000005 Leuven PET UCB-J dataset 1 in control participants ", "dataset_version": "V1", "children": [{"type": "directory", "name": "pet", "path": "sub-AN08/pet", "dataset_id": "PN000005 Leuven PET UCB-J dataset 1 in control participants ", "dataset_version": "V1"}, {"type": "directory", "name": "perf", "path": "sub-AN08/perf", "dataset_id": "PN000005 Leuven PET UCB-J dataset 1 in control participants ", "dataset_version": "V1"}, {"type": "directory", "name": "anat", "path": "sub-AN08/anat", "dataset_id": "PN000005 Leuven PET UCB-J dataset 1 in control participants ", "dataset_version": "V1"}], "path": "sub-AN08", "name": "sub-AN08"}